zvtm/__init__.py
zvtm/consts.py
zvtm/fill_project.py
zvtm/main.py
zvtm/plugin.py
zvtm/api/__init__.py
zvtm/api/intent.py
zvtm/api/kdata.py
zvtm/api/portfolio.py
zvtm/api/stats.py
zvtm/api/trader_info_api.py
zvtm/api/utils.py
zvtm/autocode/__init__.py
zvtm/autocode/generator.py
zvtm/autocode/templates/__init__.py
zvtm/contract/__init__.py
zvtm/contract/api.py
zvtm/contract/base.py
zvtm/contract/base_service.py
zvtm/contract/context.py
zvtm/contract/data_type.py
zvtm/contract/drawer.py
zvtm/contract/factor.py
zvtm/contract/normal_data.py
zvtm/contract/reader.py
zvtm/contract/recorder.py
zvtm/contract/register.py
zvtm/contract/schema.py
zvtm/contract/zvt_context.py
zvtm/contract/zvt_info.py
zvtm/domain/__init__.py
zvtm/domain/trader_info.py
zvtm/domain/actor/__init__.py
zvtm/domain/actor/actor_meta.py
zvtm/domain/actor/stock_actor.py
zvtm/domain/fundamental/__init__.py
zvtm/domain/fundamental/dividend_financing.py
zvtm/domain/fundamental/finance.py
zvtm/domain/fundamental/trading.py
zvtm/domain/fundamental/valuation.py
zvtm/domain/macro/__init__.py
zvtm/domain/macro/currency.py
zvtm/domain/macro/macro.py
zvtm/domain/meta/__init__.py
zvtm/domain/meta/block_meta.py
zvtm/domain/meta/country_meta.py
zvtm/domain/meta/etf_meta.py
zvtm/domain/meta/fund_meta.py
zvtm/domain/meta/index_meta.py
zvtm/domain/meta/indexus_meta.py
zvtm/domain/meta/stock_meta.py
zvtm/domain/meta/stockhk_meta.py
zvtm/domain/meta/stockus_meta.py
zvtm/domain/misc/__init__.py
zvtm/domain/misc/holder.py
zvtm/domain/misc/money_flow.py
zvtm/domain/misc/overall.py
zvtm/domain/misc/stock_news.py
zvtm/domain/quotes/__init__.py
zvtm/domain/quotes/trade_day.py
zvtm/domain/quotes/block/__init__.py
zvtm/domain/quotes/block/block_1d_kdata.py
zvtm/domain/quotes/block/block_1mon_kdata.py
zvtm/domain/quotes/block/block_1wk_kdata.py
zvtm/domain/quotes/etf/__init__.py
zvtm/domain/quotes/etf/etf_1d_kdata.py
zvtm/domain/quotes/index/__init__.py
zvtm/domain/quotes/index/index_1d_kdata.py
zvtm-0.0.11.dist-info/METADATA
zvtm-0.0.11.dist-info/WHEEL
zvtm-0.0.11.dist-info/entry_points.txt
zvtm-0.0.11.dist-info/top_level.txt
zvtm-0.0.11.dist-info/RECORD
